openalexapi/__init__.py
openalexapi/author.py
openalexapi/authorship.py
openalexapi/biblio.py
openalexapi/concept.py
openalexapi/ids.py
openalexapi/institution.py
openalexapi/mesh.py
openalexapi/openaccess.py
openalexapi/venue.py
openalexapi/work.py
openalexapi/year.py
openalexapi-0.0.1a0.dist-info/LICENSE
openalexapi-0.0.1a0.dist-info/METADATA
openalexapi-0.0.1a0.dist-info/WHEEL
openalexapi-0.0.1a0.dist-info/top_level.txt
openalexapi-0.0.1a0.dist-info/RECORD
